Workbook

Sheet Step 1_Config
A1: PRODUCT ID | B1: COUNTRY | C1: Product Name | D1: MARKET TYPE NAME | E1: CLEARING VENUE | F1: MIC CODE
A2: 10 | B2: NWE | C2: Brent 1st Line Future | D2: =_xlfn.XLOOKUP(A2,'ProductCodesReport '!$B:$B,'ProductCodesReport '!$K:$K,1) -> Oil | E2: =_xlfn.XLOOKUP(A2,'ProductCodesReport '!$B:$B,'ProductCodesReport '!$I:$I,1) -> ICEU | F2: =_xlfn.XLOOKUP(A2,'ProductCodesReport '!$B:$B,'ProductCodesReport '!$J:$J,1) -> IFEU
A3: 451 | B3: US | C3: AB NIT Basis Future | D3: =_xlfn.XLOOKUP(A3,'ProductCodesReport '!$B:$B,'ProductCodesReport '!$K:$K,1) -> Financial Gas | E3: =_xlfn.XLOOKUP(A3,'ProductCodesReport '!$B:$B,'ProductCodesReport '!$I:$I,1) -> ICEU | F3: =_xlfn.XLOOKUP(A3,'ProductCodesReport '!$B:$B,'ProductCodesReport '!$J:$J,1) -> IFED
A4: 14 | B4: NWE | C4: Crude Diff - Brent 1st Line vs Dubai 1st Line Future | D4: =_xlfn.XLOOKUP(A4,'ProductCodesReport '!$B:$B,'ProductCodesReport '!$K:$K,1) -> Oil | E4: =_xlfn.XLOOKUP(A4,'ProductCodesReport '!$B:$B,'ProductCodesReport '!$I:$I,1) -> ICEU | F4: =_xlfn.XLOOKUP(A4,'ProductCodesReport '!$B:$B,'ProductCodesReport '!$J:$J,1) -> IFEU
A5: 15 | B5: NWE | C5: Crude Diff - Dated Brent vs Brent 1st Line Future | D5: =_xlfn.XLOOKUP(A5,'ProductCodesReport '!$B:$B,'ProductCodesReport '!$K:$K,1) -> Oil | E5: =_xlfn.XLOOKUP(A5,'ProductCodesReport '!$B:$B,'ProductCodesReport '!$I:$I,1) -> ICEU | F5: =_xlfn.XLOOKUP(A5,'ProductCodesReport '!$B:$B,'ProductCodesReport '!$J:$J,1) -> IFEU
A6: 465 | B6: US | C6: AB NIT Index Future | D6: =_xlfn.XLOOKUP(A6,'ProductCodesReport '!$B:$B,'ProductCodesReport '!$K:$K,1) -> Financial Gas | E6: =_xlfn.XLOOKUP(A6,'ProductCodesReport '!$B:$B,'ProductCodesReport '!$I:$I,1) -> ICEU | F6: =_xlfn.XLOOKUP(A6,'ProductCodesReport '!$B:$B,'ProductCodesReport '!$J:$J,1) -> IFED
A7: 20 | B7: SGP | C7: Fuel Oil 180 CST Singapore Future | D7: =_xlfn.XLOOKUP(A7,'ProductCodesReport '!$B:$B,'ProductCodesReport '!$K:$K,1) -> Oil | E7: =_xlfn.XLOOKUP(A7,'ProductCodesReport '!$B:$B,'ProductCodesReport '!$I:$I,1) -> ICEU | F7: =_xlfn.XLOOKUP(A7,'ProductCodesReport '!$B:$B,'ProductCodesReport '!$J:$J,1) -> IFEU
A8: 20 | B8: SGP | C8: Fuel Oil 180 CST Singapore Future | D8: =_xlfn.XLOOKUP(A8,'ProductCodesReport '!$B:$B,'ProductCodesReport '!$K:$K,1) -> Oil | E8: =_xlfn.XLOOKUP(A8,'ProductCodesReport '!$B:$B,'ProductCodesReport '!$I:$I,1) -> ICEU | F8: =_xlfn.XLOOKUP(A8,'ProductCodesReport '!$B:$B,'ProductCodesReport '!$J:$J,1) -> IFEU
A9: 22 | B9: NWE | C9: Fuel Oil 3.5% FOB Rotterdam Barges Future | D9: =_xlfn.XLOOKUP(A9,'ProductCodesReport '!$B:$B,'ProductCodesReport '!$K:$K,1) -> Oil | E9: =_xlfn.XLOOKUP(A9,'ProductCodesReport '!$B:$B,'ProductCodesReport '!$I:$I,1) -> ICEU | F9: =_xlfn.XLOOKUP(A9,'ProductCodesReport '!$B:$B,'ProductCodesReport '!$J:$J,1) -> IFEU
A10: 22 | B10: NWE | C10: Fuel Oil 3.5% FOB Rotterdam Barges Future | D10: =_xlfn.XLOOKUP(A10,'ProductCodesReport '!$B:$B,'ProductCodesReport '!$K:$K,1) -> Oil | E10: =_xlfn.XLOOKUP(A10,'ProductCodesReport '!$B:$B,'ProductCodesReport '!$I:$I,1) -> ICEU | F10: =_xlfn.XLOOKUP(A10,'ProductCodesReport '!$B:$B,'ProductCodesReport '!$J:$J,1) -> IFEU
A11: 23 | B11: NWE | C11: Fuel Oil 1% FOB NWE Cargoes Future | D11: =_xlfn.XLOOKUP(A11,'ProductCodesReport '!$B:$B,'ProductCodesReport '!$K:$K,1) -> Oil | E11: =_xlfn.XLOOKUP(A11,'ProductCodesReport '!$B:$B,'ProductCodesReport '!$I:$I,1) -> ICEU | F11: =_xlfn.XLOOKUP(A11,'ProductCodesReport '!$B:$B,'ProductCodesReport '!$J:$J,1) -> IFEU
A12: 24 | B12: SGP | C12: Fuel Oil Crack - Fuel Oil 180 CST Singapore vs Dubai 1st Line Future | D12: =_xlfn.XLOOKUP(A12,'ProductCodesReport '!$B:$B,'ProductCodesReport '!$K:$K,1) -> Oil | E12: =_xlfn.XLOOKUP(A12,'ProductCodesReport '!$B:$B,'ProductCodesReport '!$I:$I,1) -> ICEU | F12: =_xlfn.XLOOKUP(A12,'ProductCodesReport '!$B:$B,'ProductCodesReport '!$J:$J,1) -> IFEU
A13: 26 | B13: NWE | C13: Fuel Oil 1% FOB NWE Cargoes vs 3.5% FOB Rotterdam Barges Swap | D13: =_xlfn.XLOOKUP(A13,'ProductCodesReport '!$B:$B,'ProductCodesReport '!$K:$K,1) -> Oil | E13: =_xlfn.XLOOKUP(A13,'ProductCodesReport '!$B:$B,'ProductCodesReport '!$I:$I,1) -> Bilateral | F13: =_xlfn.XLOOKUP(A13,'ProductCodesReport '!$B:$B,'ProductCodesReport '!$J:$J,1) -> ICES
... A23: 22105 | B23: US | C23: Agua Blanca Pool (inter) Physical Gas Daily Spot | D23: =_xlfn.XLOOKUP(A23,'ProductCodesReport '!$B:$B,'ProductCodesReport '!$K:$K,1) -> Physical Gas | E23: =_xlfn.XLOOKUP(A23,'ProductCodesReport '!$B:$B,'ProductCodesReport '!$I:$I,1) -> NGXC | F23: =_xlfn.XLOOKUP(A23,'ProductCodesReport '!$B:$B,'ProductCodesReport '!$J:$J,1) -> IEPA
A24: 183 | B24: US | C24: 1 | D24: =_xlfn.XLOOKUP(A24,'ProductCodesReport '!$B:$B,'ProductCodesReport '!$K:$K,1) -> 1 | E24: =_xlfn.XLOOKUP(A24,'ProductCodesReport '!$B:$B,'ProductCodesReport '!$I:$I,1) -> 1 | F24: =_xlfn.XLOOKUP(A24,'ProductCodesReport '!$B:$B,'ProductCodesReport '!$J:$J,1) -> 1
A25: 186 | B25: US | C25: 1 | D25: =_xlfn.XLOOKUP(A25,'ProductCodesReport '!$B:$B,'ProductCodesReport '!$K:$K,1) -> 1 | E25: =_xlfn.XLOOKUP(A25,'ProductCodesReport '!$B:$B,'ProductCodesReport '!$I:$I,1) -> 1 | F25: =_xlfn.XLOOKUP(A25,'ProductCodesReport '!$B:$B,'ProductCodesReport '!$J:$J,1) -> 1
A26: 222 | B26: MED | C26: Fuel Oil 3.5% FOB Med Cargoes Future | D26: =_xlfn.XLOOKUP(A26,'ProductCodesReport '!$B:$B,'ProductCodesReport '!$K:$K,1) -> Oil | E26: =_xlfn.XLOOKUP(A26,'ProductCodesReport '!$B:$B,'ProductCodesReport '!$I:$I,1) -> ICEU | F26: =_xlfn.XLOOKUP(A26,'ProductCodesReport '!$B:$B,'ProductCodesReport '!$J:$J,1) -> IFEU
A27: 236 | B27: UK | C27: UK NBP Natural Gas Futures | D27: =_xlfn.XLOOKUP(A27,'ProductCodesReport '!$B:$B,'ProductCodesReport '!$K:$K,1) -> IPE Natural Gas Futures | E27: =_xlfn.XLOOKUP(A27,'ProductCodesReport '!$B:$B,'ProductCodesReport '!$I:$I,1) -> ICEU | F27: =_xlfn.XLOOKUP(A27,'ProductCodesReport '!$B:$B,'ProductCodesReport '!$J:$J,1) -> IFEU
A28: 254 | B28: NWE | C28: Brent Crude Futures | D28: =_xlfn.XLOOKUP(A28,'ProductCodesReport '!$B:$B,'ProductCodesReport '!$K:$K,1) -> IPE Brent Futures | E28: =_xlfn.XLOOKUP(A28,'ProductCodesReport '!$B:$B,'ProductCodesReport '!$I:$I,1) -> ICEU | F28: =_xlfn.XLOOKUP(A28,'ProductCodesReport '!$B:$B,'ProductCodesReport '!$J:$J,1) -> IFEU
A29: 257 | B29: NWE | C29: 1 | D29: =_xlfn.XLOOKUP(A29,'ProductCodesReport '!$B:$B,'ProductCodesReport '!$K:$K,1) -> 1 | E29: =_xlfn.XLOOKUP(A29,'ProductCodesReport '!$B:$B,'ProductCodesReport '!$I:$I,1) -> 1 | F29: =_xlfn.XLOOKUP(A29,'ProductCodesReport '!$B:$B,'ProductCodesReport '!$J:$J,1) -> 1
A30: 22108 | B30: US | C30: Agua Blanca Pool (inter) Physical Inside FERC | D30: =_xlfn.XLOOKUP(A30,'ProductCodesReport '!$B:$B,'ProductCodesReport '!$K:$K,1) -> Physical Gas | E30: =_xlfn.XLOOKUP(A30,'ProductCodesReport '!$B:$B,'ProductCodesReport '!$I:$I,1) -> NGXC | F30: =_xlfn.XLOOKUP(A30,'ProductCodesReport '!$B:$B,'ProductCodesReport '!$J:$J,1) -> IEPA
A31: 266 | B31: SGP | C31: Fuel Oil Diff - Fuel Oil 180 CST Singapore vs 380 CST Singapore Future | D31: =_xlfn.XLOOKUP(A31,'ProductCodesReport '!$B:$B,'ProductCodesReport '!$K:$K,1) -> Oil | E31: =_xlfn.XLOOKUP(A31,'ProductCodesReport '!$B:$B,'ProductCodesReport '!$I:$I,1) -> ICEU | F31: =_xlfn.XLOOKUP(A31,'ProductCodesReport '!$B:$B,'ProductCodesReport '!$J:$J,1) -> IFEU
A32: 282 | B32: US | C32: 1 | D32: =_xlfn.XLOOKUP(A32,'ProductCodesReport '!$B:$B,'ProductCodesReport '!$K:$K,1) -> 1 | E32: =_xlfn.XLOOKUP(A32,'ProductCodesReport '!$B:$B,'ProductCodesReport '!$I:$I,1) -> 1 | F32: =_xlfn.XLOOKUP(A32,'ProductCodesReport '!$B:$B,'ProductCodesReport '!$J:$J,1) -> 1
A33: 286 | B33: US | C33: 1 | D33: =_xlfn.XLOOKUP(A33,'ProductCodesReport '!$B:$B,'ProductCodesReport '!$K:$K,1) -> 1 | E33: =_xlfn.XLOOKUP(A33,'ProductCodesReport '!$B:$B,'ProductCodesReport '!$I:$I,1) -> 1 | F33: =_xlfn.XLOOKUP(A33,'ProductCodesReport '!$B:$B,'ProductCodesReport '!$J:$J,1) -> 1
A34: 1881 | B34: US | C34: ANR SE (Louisiana) Basis Future | D34: =_xlfn.XLOOKUP(A34,'ProductCodesReport '!$B:$B,'ProductCodesReport '!$K:$K,1) -> Financial Gas | E34: =_xlfn.XLOOKUP(A34,'ProductCodesReport '!$B:$B,'ProductCodesReport '!$I:$I,1) -> ICEU | F34: =_xlfn.XLOOKUP(A34,'ProductCodesReport '!$B:$B,'ProductCodesReport '!$J:$J,1) -> IFED
A35: 3156 | B35: US | C35: ANR SE (Louisiana) Index Future | D35: =_xlfn.XLOOKUP(A35,'ProductCodesReport '!$B:$B,'ProductCodesReport '!$K:$K,1) -> Financial Gas | E35: =_xlfn.XLOOKUP(A35,'ProductCodesReport '!$B:$B,'ProductCodesReport '!$I:$I,1) -> ICEU | F35: =_xlfn.XLOOKUP(A35,'ProductCodesReport '!$B:$B,'ProductCodesReport '!$J:$J,1) -> IFED
A36: 289 | B36: US | C36: 1 | D36: =_xlfn.XLOOKUP(A36,'ProductCodesReport '!$B:$B,'ProductCodesReport '!$K:$K,1) -> 1 | E36: =_xlfn.XLOOKUP(A36,'ProductCodesReport '!$B:$B,'ProductCodesReport '!$I:$I,1) -> 1 | F36: =_xlfn.XLOOKUP(A36,'ProductCodesReport '!$B:$B,'ProductCodesReport '!$J:$J,1) -> 1
A37: 290 | B37: US | C37: 1 | D37: =_xlfn.XLOOKUP(A37,'ProductCodesReport '!$B:$B,'ProductCodesReport '!$K:$K,1) -> 1 | E37: =_xlfn.XLOOKUP(A37,'ProductCodesReport '!$B:$B,'ProductCodesReport '!$I:$I,1) -> 1 | F37: =_xlfn.XLOOKUP(A37,'ProductCodesReport '!$B:$B,'ProductCodesReport '!$J:$J,1) -> 1
A38: 291 | B38: US | C38: 1 | D38: =_xlfn.XLOOKUP(A38,'ProductCodesReport '!$B:$B,'ProductCodesReport '!$K:$K,1) -> 1 | E38: =_xlfn.XLOOKUP(A38,'ProductCodesReport '!$B:$B,'ProductCodesReport '!$I:$I,1) -> 1 | F38: =_xlfn.XLOOKUP(A38,'ProductCodesReport '!$B:$B,'ProductCodesReport '!$J:$J,1) -> 1
A39: 303 | B39: US | C39: 1 | D39: =_xlfn.XLOOKUP(A39,'ProductCodesReport '!$B:$B,'ProductCodesReport '!$K:$K,1) -> 1 | E39: =_xlfn.XLOOKUP(A39,'ProductCodesReport '!$B:$B,'ProductCodesReport '!$I:$I,1) -> 1 | F39: =_xlfn.XLOOKUP(A39,'ProductCodesReport '!$B:$B,'ProductCodesReport '!$J:$J,1) -> 1
A40: 316 | B40: US | C40: 1 | D40: =_xlfn.XLOOKUP(A40,'ProductCodesReport '!$B:$B,'ProductCodesReport '!$K:$K,1) -> 1 | E40: =_xlfn.XLOOKUP(A40,'ProductCodesReport '!$B:$B,'ProductCodesReport '!$I:$I,1) -> 1 | F40: =_xlfn.XLOOKUP(A40,'ProductCodesReport '!$B:$B,'ProductCodesReport '!$J:$J,1) -> 1
A41: 317 | B41: US | C41: 1 | D41: =_xlfn.XLOOKUP(A41,'ProductCodesReport '!$B:$B,'ProductCodesReport '!$K:$K,1) -> 1 | E41: =_xlfn.XLOOKUP(A41,'ProductCodesReport '!$B:$B,'ProductCodesReport '!$I:$I,1) -> 1 | F41: =_xlfn.XLOOKUP(A41,'ProductCodesReport '!$B:$B,'ProductCodesReport '!$J:$J,1) -> 1
A42: 1834 | B42: US | C42: ANR SE (Louisiana) Physical Basis LD1 | D42: =_xlfn.XLOOKUP(A42,'ProductCodesReport '!$B:$B,'ProductCodesReport '!$K:$K,1) -> Physical Gas | E42: =_xlfn.XLOOKUP(A42,'ProductCodesReport '!$B:$B,'ProductCodesReport '!$I:$I,1) -> NGXC | F42: =_xlfn.XLOOKUP(A42,'ProductCodesReport '!$B:$B,'ProductCodesReport '!$J:$J,1) -> IEPA
A43: 1830 | B43: US | C43: ANR SE (Louisiana) Physical Fixed Price Spot | D43: =_xlfn.XLOOKUP(A43,'ProductCodesReport '!$B:$B,'ProductCodesReport '!$K:$K,1) -> Physical Gas | E43: =_xlfn.XLOOKUP(A43,'ProductCodesReport '!$B:$B,'ProductCodesReport '!$I:$I,1) -> NGXC | F43: =_xlfn.XLOOKUP(A43,'ProductCodesReport '!$B:$B,'ProductCodesReport '!$J:$J,1) -> IEPA
A44: 357 | B44: US | C44: 1 | D44: =_xlfn.XLOOKUP(A44,'ProductCodesReport '!$B:$B,'ProductCodesReport '!$K:$K,1) -> 1 | E44: =_xlfn.XLOOKUP(A44,'ProductCodesReport '!$B:$B,'ProductCodesReport '!$I:$I,1) -> 1 | F44: =_xlfn.XLOOKUP(A44,'ProductCodesReport '!$B:$B,'ProductCodesReport '!$J:$J,1) -> 1
A45: 365 | B45: SGP | C45: Fuel Oil 380 CST Singapore Future | D45: =_xlfn.XLOOKUP(A45,'ProductCodesReport '!$B:$B,'ProductCodesReport '!$K:$K,1) -> Oil | E45: =_xlfn.XLOOKUP(A45,'ProductCodesReport '!$B:$B,'ProductCodesReport '!$I:$I,1) -> ICEU | F45: =_xlfn.XLOOKUP(A45,'ProductCodesReport '!$B:$B,'ProductCodesReport '!$J:$J,1) -> IFEU
A46: 365 | B46: SGP | C46: Fuel Oil 380 CST Singapore Future | D46: =_xlfn.XLOOKUP(A46,'ProductCodesReport '!$B:$B,'ProductCodesReport '!$K:$K,1) -> Oil | E46: =_xlfn.XLOOKUP(A46,'ProductCodesReport '!$B:$B,'ProductCodesReport '!$I:$I,1) -> ICEU | F46: =_xlfn.XLOOKUP(A46,'ProductCodesReport '!$B:$B,'ProductCodesReport '!$J:$J,1) -> IFEU
A47: 368 | B47: US | C47: 1 | D47: =_xlfn.XLOOKUP(A47,'ProductCodesReport '!$B:$B,'ProductCodesReport '!$K:$K,1) -> 1 | E47: =_xlfn.XLOOKUP(A47,'ProductCodesReport '!$B:$B,'ProductCodesReport '!$I:$I,1) -> 1 | F47: =_xlfn.XLOOKUP(A47,'ProductCodesReport '!$B:$B,'ProductCodesReport '!$J:$J,1) -> 1
A48: 369 | B48: US | C48: 1 | D48: =_xlfn.XLOOKUP(A48,'ProductCodesReport '!$B:$B,'ProductCodesReport '!$K:$K,1) -> 1 | E48: =_xlfn.XLOOKUP(A48,'ProductCodesReport '!$B:$B,'ProductCodesReport '!$I:$I,1) -> 1 | F48: =_xlfn.XLOOKUP(A48,'ProductCodesReport '!$B:$B,'ProductCodesReport '!$J:$J,1) -> 1
A49: 375 | B49: US | C49: 1 | D49: =_xlfn.XLOOKUP(A49,'ProductCodesReport '!$B:$B,'ProductCodesReport '!$K:$K,1) -> 1 | E49: =_xlfn.XLOOKUP(A49,'ProductCodesReport '!$B:$B,'ProductCodesReport '!$I:$I,1) -> 1 | F49: =_xlfn.XLOOKUP(A49,'ProductCodesReport '!$B:$B,'ProductCodesReport '!$J:$J,1) -> 1
A50: 376 | B50: US | C50: 1 | D50: =_xlfn.XLOOKUP(A50,'ProductCodesReport '!$B:$B,'ProductCodesReport '!$K:$K,1) -> 1 | E50: =_xlfn.XLOOKUP(A50,'ProductCodesReport '!$B:$B,'ProductCodesReport '!$I:$I,1) -> 1 | F50: =_xlfn.XLOOKUP(A50,'ProductCodesReport '!$B:$B,'ProductCodesReport '!$J:$J,1) -> 1
A51: 385 | B51: NWE | C51: 1 | D51: =_xlfn.XLOOKUP(A51,'ProductCodesReport '!$B:$B,'ProductCodesReport '!$K:$K,1) -> 1 | E51: =_xlfn.XLOOKUP(A51,'ProductCodesReport '!$B:$B,'ProductCodesReport '!$I:$I,1) -> 1 | F51: =_xlfn.XLOOKUP(A51,'ProductCodesReport '!$B:$B,'ProductCodesReport '!$J:$J,1) -> 1
A52: 390 | B52: EU | C52: EUA Futures | D52: =_xlfn.XLOOKUP(A52,'ProductCodesReport '!$B:$B,'ProductCodesReport '!$K:$K,1) -> EU Emissions Allowances | E52: =_xlfn.XLOOKUP(A52,'ProductCodesReport '!$B:$B,'ProductCodesReport '!$I:$I,1) -> ICEU | F52: =_xlfn.XLOOKUP(A52,'ProductCodesReport '!$B:$B,'ProductCodesReport '!$J:$J,1) -> NDEX
A53: 390 | B53: EU | C53: EUA Futures | D53: =_xlfn.XLOOKUP(A53,'ProductCodesReport '!$B:$B,'ProductCodesReport '!$K:$K,1) -> EU Emissions Allowances | E53: =_xlfn.XLOOKUP(A53,'ProductCodesReport '!$B:$B,'ProductCodesReport '!$I:$I,1) -> ICEU | F53: =_xlfn.XLOOKUP(A53,'ProductCodesReport '!$B:$B,'ProductCodesReport '!$J:$J,1) -> NDEX
A54: 1833 | B54: US | C54: ANR SE (Louisiana) Physical Gas Daily Spot | D54: =_xlfn.XLOOKUP(A54,'ProductCodesReport '!$B:$B,'ProductCodesReport '!$K:$K,1) -> Physical Gas | E54: =_xlfn.XLOOKUP(A54,'ProductCodesReport '!$B:$B,'ProductCodesReport '!$I:$I,1) -> NGXC | F54: =_xlfn.XLOOKUP(A54,'ProductCodesReport '!$B:$B,'ProductCodesReport '!$J:$J,1) -> IEPA
A55: 1835 | B55: US | C55: ANR SE (Louisiana) Physical Inside FERC | D55: =_xlfn.XLOOKUP(A55,'ProductCodesReport '!$B:$B,'ProductCodesReport '!$K:$K,1) -> Physical Gas | E55: =_xlfn.XLOOKUP(A55,'ProductCodesReport '!$B:$B,'ProductCodesReport '!$I:$I,1) -> NGXC | F55: =_xlfn.XLOOKUP(A55,'ProductCodesReport '!$B:$B,'ProductCodesReport '!$J:$J,1) -> IEPA
A56: 443 | B56: US | C56: ANR SW (Oklahoma) Basis Future | D56: =_xlfn.XLOOKUP(A56,'ProductCodesReport '!$B:$B,'ProductCodesReport '!$K:$K,1) -> Financial Gas | E56: =_xlfn.XLOOKUP(A56,'ProductCodesReport '!$B:$B,'ProductCodesReport '!$I:$I,1) -> ICEU | F56: =_xlfn.XLOOKUP(A56,'ProductCodesReport '!$B:$B,'ProductCodesReport '!$J:$J,1) -> IFED
A57: 3155 | B57: US | C57: ANR SW (Oklahoma) Index Future | D57: =_xlfn.XLOOKUP(A57,'ProductCodesReport '!$B:$B,'ProductCodesReport '!$K:$K,1) -> Financial Gas | E57: =_xlfn.XLOOKUP(A57,'ProductCodesReport '!$B:$B,'ProductCodesReport '!$I:$I,1) -> ICEU | F57: =_xlfn.XLOOKUP(A57,'ProductCodesReport '!$B:$B,'ProductCodesReport '!$J:$J,1) -> IFED
A58: 2981 | B58: US | C58: ANR SW (Oklahoma) Physical Fixed Price Spot | D58: =_xlfn.XLOOKUP(A58,'ProductCodesReport '!$B:$B,'ProductCodesReport '!$K:$K,1) -> Physical Gas | E58: =_xlfn.XLOOKUP(A58,'ProductCodesReport '!$B:$B,'ProductCodesReport '!$I:$I,1) -> NGXC | F58: =_xlfn.XLOOKUP(A58,'ProductCodesReport '!$B:$B,'ProductCodesReport '!$J:$J,1) -> IEPA
A59: 2982 | B59: US | C59: ANR SW (Oklahoma) Physical Gas Daily Monthly | D59: =_xlfn.XLOOKUP(A59,'ProductCodesReport '!$B:$B,'ProductCodesReport '!$K:$K,1) -> Physical Gas | E59: =_xlfn.XLOOKUP(A59,'ProductCodesReport '!$B:$B,'ProductCodesReport '!$I:$I,1) -> NGXC | F59: =_xlfn.XLOOKUP(A59,'ProductCodesReport '!$B:$B,'ProductCodesReport '!$J:$J,1) -> IEPA
A60: 2984 | B60: US | C60: ANR SW (Oklahoma) Physical Gas Daily Spot | D60: =_xlfn.XLOOKUP(A60,'ProductCodesReport '!$B:$B,'ProductCodesReport '!$K:$K,1) -> Physical Gas | E60: =_xlfn.XLOOKUP(A60,'ProductCodesReport '!$B:$B,'ProductCodesReport '!$I:$I,1) -> NGXC | F60: =_xlfn.XLOOKUP(A60,'ProductCodesReport '!$B:$B,'ProductCodesReport '!$J:$J,1) -> IEPA
A61: 3160 | B61: US | C61: ANR SW (Oklahoma) Swing Future | D61: =_xlfn.XLOOKUP(A61,'ProductCodesReport '!$B:$B,'ProductCodesReport '!$K:$K,1) -> Financial Gas | E61: =_xlfn.XLOOKUP(A61,'ProductCodesReport '!$B:$B,'ProductCodesReport '!$I:$I,1) -> ICEU | F61: =_xlfn.XLOOKUP(A61,'ProductCodesReport '!$B:$B,'ProductCodesReport '!$J:$J,1) -> IFED
A62: 426 | B62: US | C62: 1 | D62: =_xlfn.XLOOKUP(A62,'ProductCodesReport '!$B:$B,'ProductCodesReport '!$K:$K,1) -> 1 | E62: =_xlfn.XLOOKUP(A62,'ProductCodesReport '!$B:$B,'ProductCodesReport '!$I:$I,1) -> 1 | F62: =_xlfn.XLOOKUP(A62,'ProductCodesReport '!$B:$B,'ProductCodesReport '!$J:$J,1) -> 1
A63: 2985 | B63: US | C63: ANR SW Physical Inside FERC | D63: =_xlfn.XLOOKUP(A63,'ProductCodesReport '!$B:$B,'ProductCodesReport '!$K:$K,1) -> Physical Gas | E63: =_xlfn.XLOOKUP(A63,'ProductCodesReport '!$B:$B,'ProductCodesReport '!$I:$I,1) -> NGXC | F63: =_xlfn.XLOOKUP(A63,'ProductCodesReport '!$B:$B,'ProductCodesReport '!$J:$J,1) -> IEPA
A64: 2986 | B64: US | C64: ANR-SW Physical Basis LD1 | D64: =_xlfn.XLOOKUP(A64,'ProductCodesReport '!$B:$B,'ProductCodesReport '!$K:$K,1) -> Physical Gas | E64: =_xlfn.XLOOKUP(A64,'ProductCodesReport '!$B:$B,'ProductCodesReport '!$I:$I,1) -> NGXC | F64: =_xlfn.XLOOKUP(A64,'ProductCodesReport '!$B:$B,'ProductCodesReport '!$J:$J,1) -> IEPA
A65: 6375 | B65: US | C65: APC ACE Physical Fixed Price Spot | D65: =_xlfn.XLOOKUP(A65,'ProductCodesReport '!$B:$B,'ProductCodesReport '!$K:$K,1) -> Physical Gas | E65: =_xlfn.XLOOKUP(A65,'ProductCodesReport '!$B:$B,'ProductCodesReport '!$I:$I,1) -> NGXC | F65: =_xlfn.XLOOKUP(A65,'ProductCodesReport '!$B:$B,'ProductCodesReport '!$J:$J,1) -> IEPA
A66: 6374 | B66: US | C66: APC ACE Physical Gas Daily Monthly | D66: =_xlfn.XLOOKUP(A66,'ProductCodesReport '!$B:$B,'ProductCodesReport '!$K:$K,1) -> Physical Gas | E66: =_xlfn.XLOOKUP(A66,'ProductCodesReport '!$B:$B,'ProductCodesReport '!$I:$I,1) -> NGXC | F66: =_xlfn.XLOOKUP(A66,'ProductCodesReport '!$B:$B,'ProductCodesReport '!$J:$J,1) -> IEPA
A67: 6372 | B67: US | C67: APC ACE Physical Gas Daily Spot | D67: =_xlfn.XLOOKUP(A67,'ProductCodesReport '!$B:$B,'ProductCodesReport '!$K:$K,1) -> Physical Gas | E67: =_xlfn.XLOOKUP(A67,'ProductCodesReport '!$B:$B,'ProductCodesReport '!$I:$I,1) -> NGXC | F67: =_xlfn.XLOOKUP(A67,'ProductCodesReport '!$B:$B,'ProductCodesReport '!$J:$J,1) -> IEPA
A68: 6370 | B68: US | C68: APC ACE Physical Natural Gas Intelligence | D68: =_xlfn.XLOOKUP(A68,'ProductCodesReport '!$B:$B,'ProductCodesReport '!$K:$K,1) -> Physical Gas | E68: =_xlfn.XLOOKUP(A68,'ProductCodesReport '!$B:$B,'ProductCodesReport '!$I:$I,1) -> NGXC | F68: =_xlfn.XLOOKUP(A68,'ProductCodesReport '!$B:$B,'ProductCodesReport '!$J:$J,1) -> IEPA
A69: 27580 | B69: US | C69: Biofuel Outright - D3 RINs (OPIS) Current Year Future | D69: =_xlfn.XLOOKUP(A69,'ProductCodesReport '!$B:$B,'ProductCodesReport '!$K:$K,1) -> Oil Americas | E69: =_xlfn.XLOOKUP(A69,'ProductCodesReport '!$B:$B,'ProductCodesReport '!$I:$I,1) -> ICEU | F69: =_xlfn.XLOOKUP(A69,'ProductCodesReport '!$B:$B,'ProductCodesReport '!$J:$J,1) -> IFED
A70: 21781 | B70: US | C70: Biofuel Outright - D4 RINS (OPIS) Future | D70: =_xlfn.XLOOKUP(A70,'ProductCodesReport '!$B:$B,'ProductCodesReport '!$K:$K,1) -> Oil Americas | E70: =_xlfn.XLOOKUP(A70,'ProductCodesReport '!$B:$B,'ProductCodesReport '!$I:$I,1) -> ICEU | F70: =_xlfn.XLOOKUP(A70,'ProductCodesReport '!$B:$B,'ProductCodesReport '!$J:$J,1) -> IFED
A71: 21781 | B71: US | C71: Biofuel Outright - D4 RINS (OPIS) Future | D71: =_xlfn.XLOOKUP(A71,'ProductCodesReport '!$B:$B,'ProductCodesReport '!$K:$K,1) -> Oil Americas | E71: =_xlfn.XLOOKUP(A71,'ProductCodesReport '!$B:$B,'ProductCodesReport '!$I:$I,1) -> ICEU | F71: =_xlfn.XLOOKUP(A71,'ProductCodesReport '!$B:$B,'ProductCodesReport '!$J:$J,1) -> IFED
A72: 20499 | B72: US | C72: Biofuel Outright - D6 RINs (OPIS) Future | D72: =_xlfn.XLOOKUP(A72,'ProductCodesReport '!$B:$B,'ProductCodesReport '!$K:$K,1) -> Oil Americas | E72: =_xlfn.XLOOKUP(A72,'ProductCodesReport '!$B:$B,'ProductCodesReport '!$I:$I,1) -> ICEU | F72: =_xlfn.XLOOKUP(A72,'ProductCodesReport '!$B:$B,'ProductCodesReport '!$J:$J,1) -> IFED
A73: 19253 | B73: US | C73: Caiso Malin Day-Ahead Peak Daily Fixed Price Future | D73: =_xlfn.XLOOKUP(A73,'ProductCodesReport '!$B:$B,'ProductCodesReport '!$K:$K,1) -> Financial Power | E73: =_xlfn.XLOOKUP(A73,'ProductCodesReport '!$B:$B,'ProductCodesReport '!$I:$I,1) -> ICEU | F73: =_xlfn.XLOOKUP(A73,'ProductCodesReport '!$B:$B,'ProductCodesReport '!$J:$J,1) -> IFED
A74: 23764 | B74: US | C74: CAISO NP-15 Day-Ahead HE 0900-1600 Fixed Price Future, 7X | D74: =_xlfn.XLOOKUP(A74,'ProductCodesReport '!$B:$B,'ProductCodesReport '!$K:$K,1) -> Financial Power | E74: =_xlfn.XLOOKUP(A74,'ProductCodesReport '!$B:$B,'ProductCodesReport '!$I:$I,1) -> ICEU | F74: =_xlfn.XLOOKUP(A74,'ProductCodesReport '!$B:$B,'ProductCodesReport '!$J:$J,1) -> IFED
... A113: 1590 | B113: US | C113: CG Onshore Physical Inside FERC | D113: =_xlfn.XLOOKUP(A113,'ProductCodesReport '!$B:$B,'ProductCodesReport '!$K:$K,1) -> Physical Gas | E113: =_xlfn.XLOOKUP(A113,'ProductCodesReport '!$B:$B,'ProductCodesReport '!$I:$I,1) -> NGXC | F113: =_xlfn.XLOOKUP(A113,'ProductCodesReport '!$B:$B,'ProductCodesReport '!$J:$J,1) -> IEPA
A114: 493 | B114: US | C114: 1 | D114: =_xlfn.XLOOKUP(A114,'ProductCodesReport '!$B:$B,'ProductCodesReport '!$K:$K,1) -> 1 | E114: =_xlfn.XLOOKUP(A114,'ProductCodesReport '!$B:$B,'ProductCodesReport '!$I:$I,1) -> 1 | F114: =_xlfn.XLOOKUP(A114,'ProductCodesReport '!$B:$B,'ProductCodesReport '!$J:$J,1) -> 1
A115: 2071 | B115: US | C115: CG-Mainline Basis Future | D115: =_xlfn.XLOOKUP(A115,'ProductCodesReport '!$B:$B,'ProductCodesReport '!$K:$K,1) -> Financial Gas | E115: =_xlfn.XLOOKUP(A115,'ProductCodesReport '!$B:$B,'ProductCodesReport '!$I:$I,1) -> ICEU | F115: =_xlfn.XLOOKUP(A115,'ProductCodesReport '!$B:$B,'ProductCodesReport '!$J:$J,1) -> IFED
A116: 497 | B116: US | C116: 1 | D116: =_xlfn.XLOOKUP(A116,'ProductCodesReport '!$B:$B,'ProductCodesReport '!$K:$K,1) -> 1 | E116: =_xlfn.XLOOKUP(A116,'ProductCodesReport '!$B:$B,'ProductCodesReport '!$I:$I,1) -> 1 | F116: =_xlfn.XLOOKUP(A116,'ProductCodesReport '!$B:$B,'ProductCodesReport '!$J:$J,1) -> 1
A117: 3961 | B117: US | C117: CG-Mainline Index Future | D117: =_xlfn.XLOOKUP(A117,'ProductCodesReport '!$B:$B,'ProductCodesReport '!$K:$K,1) -> Financial Gas | E117: =_xlfn.XLOOKUP(A117,'ProductCodesReport '!$B:$B,'ProductCodesReport '!$I:$I,1) -> ICEU | F117: =_xlfn.XLOOKUP(A117,'ProductCodesReport '!$B:$B,'ProductCodesReport '!$J:$J,1) -> IFED
A118: 3962 | B118: US | C118: CG-Mainline Swing Future | D118: =_xlfn.XLOOKUP(A118,'ProductCodesReport '!$B:$B,'ProductCodesReport '!$K:$K,1) -> Financial Gas | E118: =_xlfn.XLOOKUP(A118,'ProductCodesReport '!$B:$B,'ProductCodesReport '!$I:$I,1) -> ICEU | F118: =_xlfn.XLOOKUP(A118,'ProductCodesReport '!$B:$B,'ProductCodesReport '!$J:$J,1) -> IFED
A119: 23584 | B119: US | C119: Cheyenne Hub Swing Future | D119: =_xlfn.XLOOKUP(A119,'ProductCodesReport '!$B:$B,'ProductCodesReport '!$K:$K,1) -> Financial Gas | E119: =_xlfn.XLOOKUP(A119,'ProductCodesReport '!$B:$B,'ProductCodesReport '!$I:$I,1) -> ICEU | F119: =_xlfn.XLOOKUP(A119,'ProductCodesReport '!$B:$B,'ProductCodesReport '!$J:$J,1) -> IFED
A120: 4161 | B120: US | C120: Cheyenne Physical Basis LD1 | D120: =_xlfn.XLOOKUP(A120,'ProductCodesReport '!$B:$B,'ProductCodesReport '!$K:$K,1) -> Physical Gas | E120: =_xlfn.XLOOKUP(A120,'ProductCodesReport '!$B:$B,'ProductCodesReport '!$I:$I,1) -> NGXC | F120: =_xlfn.XLOOKUP(A120,'ProductCodesReport '!$B:$B,'ProductCodesReport '!$J:$J,1) -> IEPA
A121: 4153 | B121: US | C121: Cheyenne Physical Fixed Price Monthly | D121: =_xlfn.XLOOKUP(A121,'ProductCodesReport '!$B:$B,'ProductCodesReport '!$K:$K,1) -> Physical Gas | E121: =_xlfn.XLOOKUP(A121,'ProductCodesReport '!$B:$B,'ProductCodesReport '!$I:$I,1) -> NGXC | F121: =_xlfn.XLOOKUP(A121,'ProductCodesReport '!$B:$B,'ProductCodesReport '!$J:$J,1) -> IEPA
A122: 515 | B122: US | C122: 1 | D122: =_xlfn.XLOOKUP(A122,'ProductCodesReport '!$B:$B,'ProductCodesReport '!$K:$K,1) -> 1 | E122: =_xlfn.XLOOKUP(A122,'ProductCodesReport '!$B:$B,'ProductCodesReport '!$I:$I,1) -> 1 | F122: =_xlfn.XLOOKUP(A122,'ProductCodesReport '!$B:$B,'ProductCodesReport '!$J:$J,1) -> 1
A123: 516 | B123: NWE | C123: Fuel Oil Crack - Fuel Oil 3.5% FOB Rotterdam Barges vs Brent 1st Line Future | D123: =_xlfn.XLOOKUP(A123,'ProductCodesReport '!$B:$B,'ProductCodesReport '!$K:$K,1) -> Oil | E123: =_xlfn.XLOOKUP(A123,'ProductCodesReport '!$B:$B,'ProductCodesReport '!$I:$I,1) -> ICEU | F123: =_xlfn.XLOOKUP(A123,'ProductCodesReport '!$B:$B,'ProductCodesReport '!$J:$J,1) -> IFEU
A124: 517 | B124: GLOBAL | C124: API2 Rotterdam Coal Futures | D124: =_xlfn.XLOOKUP(A124,'ProductCodesReport '!$B:$B,'ProductCodesReport '!$K:$K,1) -> ICE Rotterdam Coal Futures | E124: =_xlfn.XLOOKUP(A124,'ProductCodesReport '!$B:$B,'ProductCodesReport '!$I:$I,1) -> ICEU | F124: =_xlfn.XLOOKUP(A124,'ProductCodesReport '!$B:$B,'ProductCodesReport '!$J:$J,1) -> IFEU
A125: 519 | B125: GLOBAL | C125: API4 Richards Bay Coal Futures | D125: =_xlfn.XLOOKUP(A125,'ProductCodesReport '!$B:$B,'ProductCodesReport '!$K:$K,1) -> ICE Richards Bay Coal Futures | E125: =_xlfn.XLOOKUP(A125,'ProductCodesReport '!$B:$B,'ProductCodesReport '!$I:$I,1) -> ICEU | F125: =_xlfn.XLOOKUP(A125,'ProductCodesReport '!$B:$B,'ProductCodesReport '!$J:$J,1) -> IFEU
A126: 527 | B126: US | C126: 1 | D126: =_xlfn.XLOOKUP(A126,'ProductCodesReport '!$B:$B,'ProductCodesReport '!$K:$K,1) -> 1 | E126: =_xlfn.XLOOKUP(A126,'ProductCodesReport '!$B:$B,'ProductCodesReport '!$I:$I,1) -> 1 | F126: =_xlfn.XLOOKUP(A126,'ProductCodesReport '!$B:$B,'ProductCodesReport '!$J:$J,1) -> 1
A127: 528 | B127: US | C127: 1 | D127: =_xlfn.XLOOKUP(A127,'ProductCodesReport '!$B:$B,'ProductCodesReport '!$K:$K,1) -> 1 | E127: =_xlfn.XLOOKUP(A127,'ProductCodesReport '!$B:$B,'ProductCodesReport '!$I:$I,1) -> 1 | F127: =_xlfn.XLOOKUP(A127,'ProductCodesReport '!$B:$B,'ProductCodesReport '!$J:$J,1) -> 1
A128: 530 | B128: US | C128: 1 | D128: =_xlfn.XLOOKUP(A128,'ProductCodesReport '!$B:$B,'ProductCodesReport '!$K:$K,1) -> 1 | E128: =_xlfn.XLOOKUP(A128,'ProductCodesReport '!$B:$B,'ProductCodesReport '!$I:$I,1) -> 1 | F128: =_xlfn.XLOOKUP(A128,'ProductCodesReport '!$B:$B,'ProductCodesReport '!$J:$J,1) -> 1
A129: 542 | B129: US | C129: 1 | D129: =_xlfn.XLOOKUP(A129,'ProductCodesReport '!$B:$B,'ProductCodesReport '!$K:$K,1) -> 1 | E129: =_xlfn.XLOOKUP(A129,'ProductCodesReport '!$B:$B,'ProductCodesReport '!$I:$I,1) -> 1 | F129: =_xlfn.XLOOKUP(A129,'ProductCodesReport '!$B:$B,'ProductCodesReport '!$J:$J,1) -> 1
A130: 543 | B130: US | C130: 1 | D130: =_xlfn.XLOOKUP(A130,'ProductCodesReport '!$B:$B,'ProductCodesReport '!$K:$K,1) -> 1 | E130: =_xlfn.XLOOKUP(A130,'ProductCodesReport '!$B:$B,'ProductCodesReport '!$I:$I,1) -> 1 | F130: =_xlfn.XLOOKUP(A130,'ProductCodesReport '!$B:$B,'ProductCodesReport '!$J:$J,1) -> 1
A131: 544 | B131: US | C131: 1 | D131: =_xlfn.XLOOKUP(A131,'ProductCodesReport '!$B:$B,'ProductCodesReport '!$K:$K,1) -> 1 | E131: =_xlfn.XLOOKUP(A131,'ProductCodesReport '!$B:$B,'ProductCodesReport '!$I:$I,1) -> 1 | F131: =_xlfn.XLOOKUP(A131,'ProductCodesReport '!$B:$B,'ProductCodesReport '!$J:$J,1) -> 1
A132: 4157 | B132: US | C132: Cheyenne Physical Fixed Price Spot | D132: =_xlfn.XLOOKUP(A132,'ProductCodesReport '!$B:$B,'ProductCodesReport '!$K:$K,1) -> Physical Gas | E132: =_xlfn.XLOOKUP(A132,'ProductCodesReport '!$B:$B,'ProductCodesReport '!$I:$I,1) -> NGXC | F132: =_xlfn.XLOOKUP(A132,'ProductCodesReport '!$B:$B,'ProductCodesReport '!$J:$J,1) -> IEPA
A133: 4158 | B133: US | C133: Cheyenne Physical Gas Daily Monthly | D133: =_xlfn.XLOOKUP(A133,'ProductCodesReport '!$B:$B,'ProductCodesReport '!$K:$K,1) -> Physical Gas | E133: =_xlfn.XLOOKUP(A133,'ProductCodesReport '!$B:$B,'ProductCodesReport '!$I:$I,1) -> NGXC | F133: =_xlfn.XLOOKUP(A133,'ProductCodesReport '!$B:$B,'ProductCodesReport '!$J:$J,1) -> IEPA
A134: 4160 | B134: US | C134: Cheyenne Physical Gas Daily Spot | D134: =_xlfn.XLOOKUP(A134,'ProductCodesReport '!$B:$B,'ProductCodesReport '!$K:$K,1) -> Physical Gas | E134: =_xlfn.XLOOKUP(A134,'ProductCodesReport '!$B:$B,'ProductCodesReport '!$I:$I,1) -> NGXC | F134: =_xlfn.XLOOKUP(A134,'ProductCodesReport '!$B:$B,'ProductCodesReport '!$J:$J,1) -> IEPA
A135: 4162 | B135: US | C135: Cheyenne Physical Inside FERC | D135: =_xlfn.XLOOKUP(A135,'ProductCodesReport '!$B:$B,'ProductCodesReport '!$K:$K,1) -> Physical Gas | E135: =_xlfn.XLOOKUP(A135,'ProductCodesReport '!$B:$B,'ProductCodesReport '!$I:$I,1) -> NGXC | F135: =_xlfn.XLOOKUP(A135,'ProductCodesReport '!$B:$B,'ProductCodesReport '!$J:$J,1) -> IEPA
A136: 452 | B136: US | C136: Chicago Basis Future | D136: =_xlfn.XLOOKUP(A136,'ProductCodesReport '!$B:$B,'ProductCodesReport '!$K:$K,1) -> Financial Gas | E136: =_xlfn.XLOOKUP(A136,'ProductCodesReport '!$B:$B,'ProductCodesReport '!$I:$I,1) -> ICEU | F136: =_xlfn.XLOOKUP(A136,'ProductCodesReport '!$B:$B,'ProductCodesReport '!$J:$J,1) -> IFED
A137: 462 | B137: US | C137: Chicago Index Future | D137: =_xlfn.XLOOKUP(A137,'ProductCodesReport '!$B:$B,'ProductCodesReport '!$K:$K,1) -> Financial Gas | E137: =_xlfn.XLOOKUP(A137,'ProductCodesReport '!$B:$B,'ProductCodesReport '!$I:$I,1) -> ICEU | F137: =_xlfn.XLOOKUP(A137,'ProductCodesReport '!$B:$B,'ProductCodesReport '!$J:$J,1) -> IFED
A138: 466 | B138: US | C138: Chicago Swing Future | D138: =_xlfn.XLOOKUP(A138,'ProductCodesReport '!$B:$B,'ProductCodesReport '!$K:$K,1) -> Financial Gas | E138: =_xlfn.XLOOKUP(A138,'ProductCodesReport '!$B:$B,'ProductCodesReport '!$I:$I,1) -> ICEU | F138: =_xlfn.XLOOKUP(A138,'ProductCodesReport '!$B:$B,'ProductCodesReport '!$J:$J,1) -> IFED
A139: 442 | B139: US | C139: CIG Rockies Basis Future | D139: =_xlfn.XLOOKUP(A139,'ProductCodesReport '!$B:$B,'ProductCodesReport '!$K:$K,1) -> Financial Gas | E139: =_xlfn.XLOOKUP(A139,'ProductCodesReport '!$B:$B,'ProductCodesReport '!$I:$I,1) -> ICEU | F139: =_xlfn.XLOOKUP(A139,'ProductCodesReport '!$B:$B,'ProductCodesReport '!$J:$J,1) -> IFED
A140: 3050 | B140: US | C140: CIG Rockies Index Future | D140: =_xlfn.XLOOKUP(A140,'ProductCodesReport '!$B:$B,'ProductCodesReport '!$K:$K,1) -> Financial Gas | E140: =_xlfn.XLOOKUP(A140,'ProductCodesReport '!$B:$B,'ProductCodesReport '!$I:$I,1) -> ICEU | F140: =_xlfn.XLOOKUP(A140,'ProductCodesReport '!$B:$B,'ProductCodesReport '!$J:$J,1) -> IFED
A141: 3058 | B141: US | C141: CIG Rockies Swing Future | D141: =_xlfn.XLOOKUP(A141,'ProductCodesReport '!$B:$B,'ProductCodesReport '!$K:$K,1) -> Financial Gas | E141: =_xlfn.XLOOKUP(A141,'ProductCodesReport '!$B:$B,'ProductCodesReport '!$I:$I,1) -> ICEU | F141: =_xlfn.XLOOKUP(A141,'ProductCodesReport '!$B:$B,'ProductCodesReport '!$J:$J,1) -> IFED
A142: 568 | B142: US | C142: 1 | D142: =_xlfn.XLOOKUP(A142,'ProductCodesReport '!$B:$B,'ProductCodesReport '!$K:$K,1) -> 1 | E142: =_xlfn.XLOOKUP(A142,'ProductCodesReport '!$B:$B,'ProductCodesReport '!$I:$I,1) -> 1 | F142: =_xlfn.XLOOKUP(A142,'ProductCodesReport '!$B:$B,'ProductCodesReport '!$J:$J,1) -> 1
A143: 576 | B143: US | C143: 1 | D143: =_xlfn.XLOOKUP(A143,'ProductCodesReport '!$B:$B,'ProductCodesReport '!$K:$K,1) -> 1 | E143: =_xlfn.XLOOKUP(A143,'ProductCodesReport '!$B:$B,'ProductCodesReport '!$I:$I,1) -> 1 | F143: =_xlfn.XLOOKUP(A143,'ProductCodesReport '!$B:$B,'ProductCodesReport '!$J:$J,1) -> 1
A144: 617 | B144: Middle East | C144: 1 | D144: =_xlfn.XLOOKUP(A144,'ProductCodesReport '!$B:$B,'ProductCodesReport '!$K:$K,1) -> 1 | E144: =_xlfn.XLOOKUP(A144,'ProductCodesReport '!$B:$B,'ProductCodesReport '!$I:$I,1) -> 1 | F144: =_xlfn.XLOOKUP(A144,'ProductCodesReport '!$B:$B,'ProductCodesReport '!$J:$J,1) -> 1
A145: 619 | B145: Middle East | C145: 1 | D145: =_xlfn.XLOOKUP(A145,'ProductCodesReport '!$B:$B,'ProductCodesReport '!$K:$K,1) -> 1 | E145: =_xlfn.XLOOKUP(A145,'ProductCodesReport '!$B:$B,'ProductCodesReport '!$I:$I,1) -> 1 | F145: =_xlfn.XLOOKUP(A145,'ProductCodesReport '!$B:$B,'ProductCodesReport '!$J:$J,1) -> 1
A146: 661 | B146: US | C146: 1 | D146: =_xlfn.XLOOKUP(A146,'ProductCodesReport '!$B:$B,'ProductCodesReport '!$K:$K,1) -> 1 | E146: =_xlfn.XLOOKUP(A146,'ProductCodesReport '!$B:$B,'ProductCodesReport '!$I:$I,1) -> 1 | F146: =_xlfn.XLOOKUP(A146,'ProductCodesReport '!$B:$B,'ProductCodesReport '!$J:$J,1) -> 1
A147: 663 | B147: US | C147: 1 | D147: =_xlfn.XLOOKUP(A147,'ProductCodesReport '!$B:$B,'ProductCodesReport '!$K:$K,1) -> 1 | E147: =_xlfn.XLOOKUP(A147,'ProductCodesReport '!$B:$B,'ProductCodesReport '!$I:$I,1) -> 1 | F147: =_xlfn.XLOOKUP(A147,'ProductCodesReport '!$B:$B,'ProductCodesReport '!$J:$J,1) -> 1
...

Sheet Step 2_Kew Words
A1: COUNTRY | B1: Product (ProductCodesReport) | C1: Market Type Name (ProductCodesReport ) | D1: MIC CODE (ProductCodesReport )
A2: UK | B2: UK
A3: UK | B3: UKA
A4: SGP | B4: Singapore
A5: NWE | B5: NWE
A6: NWE | B6: Dated Brent
A7: NWE | B7: Eurobob
A8: NWE | B8: ARA
A9: NWE | B9: Brent
A10: NWE | B10: UKC
A11: NL | B11: Dutch TTF
A12: NL | B12: Dutch Power
A13: NL | B13: FOB Rotterdam
... A39: BE | B39: ZEE
A40: CA | C40: Canadian Oilseeds
A41: CA | D41: NGXC
A42: US | B42: CAISO
A43: US | B43: California
A44: US | B44: Oklahoma
A45: US | B45: Chicago
A46: US | B46: AB NIT
A47: US | B47: Agua Blanca Pool
A48: US | B48: ANR SW
A49: US | B49: ANR
A50: US | B50: APC ACE
A51: US | B51: (OPIS)
A52: US | B52: CG Mainline
A53: US | B53: CG Onshore
... A132: US | B132: Algonquin
A133: US | C133: Oil Americas
A134: US | C134: Henry Hub
A135: Global | B135: TD
A136: Global | B136: SYN 1a
A137: Global | B137: Northwest Europe to USAC

Sheet Step 3_Kew Words
A1: COUNTRY | B1: tag 9063/9062 | C1: tag 9301/320 | D1: tag 308
A2: UK | B2: UK
A3: UK | B3: UKA
A4: SGP | B4: Singapore
A5: NWE | B5: NWE
A6: NWE | B6: Dated Brent
A7: NWE | B7: Eurobob
A8: NWE | B8: ARA
A9: NWE | B9: Brent
A10: NWE | B10: UKC
A11: NL | B11: Dutch TTF
A12: NL | B12: Dutch Power
A13: NL | B13: FOB Rotterdam
... A39: BE | B39: ZEE
A40: CA | C40: Canadian Oilseeds
A41: CA | D41: NGXC
A42: US | B42: CAISO
A43: US | B43: California
A44: US | B44: Oklahoma
A45: US | B45: Chicago
A46: US | B46: AB NIT
A47: US | B47: Agua Blanca Pool
A48: US | B48: ANR SW
A49: US | B49: ANR
A50: US | B50: APC ACE
A51: US | B51: (OPIS)
A52: US | B52: CG Mainline
A53: US | B53: CG Onshore
... A132: US | B132: Algonquin
A133: US | C133: Oil Americas
A134: US | C134: Henry Hub
A135: Global | B135: TD
A136: Global | B136: SYN 1a

Sheet ProductCodesReport 
A1: PRODUCT (Click to open in Browser) | B1: PRODUCT ID | C1: PHYSICAL | D1: LOGICAL | E1: GMI FC | F1: R&N A.C.N | G1: GROUP | H1: CLEARING ADMIN | I1: CLEARING VENUE | J1: MIC CODE | K1: MARKET TYPE NAME | L1: SYMBOL CODE
A2: Brent 1st Line Future | B2: 10 | C2: I | D2: BRN | E2: BS | F2: P997 | G2: Crude Oil and Refined Products | H2: Crude Outrights | I2: ICEU | J2: IFEU | K2: Oil | L2: BSP
A3: WTI 1st Line Future | B3: 13 | C3: R | D3: WBS | E3: WS | F3: P996 | G3: Crude Oil and Refined Products | H3: Am Crude | I3: ICEU | J3: IFED | K3: Oil Americas | L3: WSP
A4: Crude Diff - Brent 1st Line vs Dubai 1st Line Future | B4: 14 | C4: BOD | D4: BOD | E4: BO | F4: SF34 | G4: Crude Oil and Refined Products | H4: Crude Diffs | I4: ICEU | J4: IFEU | K4: Oil | L4: BOD
A5: Crude Diff - Dated Brent vs Brent 1st Line Future | B5: 15 | C5: DBF | D5: DBF | G5: Crude Oil and Refined Products | H5: Crude Diffs | I5: ICEU | J5: IFEU | K5: Oil | L5: DBF
A6: Fuel Oil Outright - New York 1% Fuel Oil Future | B6: 19 | C6: FOW | D6: FOW | E6: Q6 | G6: Crude Oil and Refined Products | H6: Am Ref bbl | I6: ICEU | J6: IFED | K6: Oil Americas | L6: FOW
A7: Fuel Oil 180 CST Singapore Future | B7: 20 | C7: SZS | D7: SZS | E7: PE | F7: NM86 | G7: Crude Oil and Refined Products | H7: Ref Outright mt | I7: ICEU | J7: IFEU | K7: Oil | L7: SZS
A8: Fuel Oil 180 CST Singapore Swap | B8: 20 | C8: SZS | D8: SZS | E8: PE | F8: NM86 | G8: Crude Oil and Refined | H8: Ref Outright mt | I8: Bilateral | J8: ICES | K8: Oil | L8: SZS
A9: Fuel Oil 3.5% FOB Rotterdam Barges Future | B9: 22 | C9: BAR | D9: BAR | E9: PG | F9: NM88 | G9: Crude Oil and Refined Products | H9: Ref Outright mt | I9: ICEU | J9: IFEU | K9: Oil | L9: BAR
A10: Fuel Oil 3.5% FOB Rotterdam Barges Swap | B10: 22 | C10: BAR | D10: BAR | E10: PG | F10: NM88 | G10: Crude Oil and Refined | H10: Ref Outright mt | I10: Bilateral | J10: ICES | K10: Oil | L10: BAR
A11: Fuel Oil 1% FOB NWE Cargoes Future | B11: 23 | C11: CAR | D11: CAR | E11: OZ | F11: NM83 | G11: Crude Oil and Refined Products | H11: Ref Outright mt | I11: ICEU | J11: IFEU | K11: Oil | L11: CAR
A12: Fuel Oil 1% FOB NWE Cargoes Swap | B12: 23 | C12: CAR | D12: CAR | E12: OZ | F12: NM83 | G12: Crude Oil and Refined | H12: Ref Outright mt | I12: Bilateral | J12: ICES | K12: Oil | L12: CAR
A13: Fuel Oil Crack - Fuel Oil 180 CST Singapore vs Dubai 1st Line Future | B13: 24 | C13: SES | D13: SES | E13: ML | G13: Crude Oil and Refined Products | H13: Cracks mt | I13: ICEU | J13: IFEU | K13: Oil | L13: SES
A14: Fuel Oil 1% FOB NWE Cargoes vs 3.5% FOB Rotterdam Barges Swap | B14: 26 | C14: FOS | D14: FOS | E14: OX | F14: NM81 | G14: Crude Oil and Refined | H14: Ref Diffs mt | I14: Bilateral | J14: ICES | K14: Oil | L14: FOS
A15: Fuel Oil Diff - Fuel Oil 1% FOB NWE Cargoes vs 3.5% FOB Rotterdam Barges Future | B15: 26 | C15: FOS | D15: FOS | E15: OX | F15: NM81 | G15: Crude Oil and Refined Products | H15: Ref Diffs mt | I15: ICEU | J15: IFEU | K15: Oil | L15: FOS
A16: Heating Oil 1st Line Future | B16: 39 | C16: HOF | D16: UHO | E16: HF | F16: QH59 | G16: Crude Oil and Refined Products | H16: Am Ref bbl | I16: ICEU | J16: IFED | K16: Oil Americas | L16: HOF
A17: Henry LD1 Fixed Price Future | B17: 53 | C17: H | D17: HNG | E17: NN | F17: R754 | G17: Natural Gas | H17: Henry Nat Gas | I17: ICEU | J17: IFED | K17: Henry Hub | L17: HNG
A18: Fuel Oil 3.5% FOB Med Cargoes vs 3.5% FOB Rotterdam Barges Swap | B18: 87 | C18: NVS | D18: NVS | E18: PB | F18: NM85 | G18: Crude Oil and Refined | H18: Ref Diffs mt | I18: Bilateral | J18: ICES | K18: Oil | L18: NVS
A19: Fuel Oil Diff - Fuel Oil 3.5% FOB Med Cargoes vs 3.5% FOB Rotterdam Barges Future | B19: 87 | C19: NVS | D19: NVS | E19: PB | F19: NM85 | G19: Crude Oil and Refined Products | H19: Ref Diffs mt | I19: ICEU | J19: IFEU | K19: Oil | L19: NVS
A20: Fuel Oil Diff - Fuel Oil 180 CST Singapore vs. 3.5% FOB Rotterdam Barges Swap | B20: 88 | C20: SFS | D20: SFS | E20: OW | F20: NM80 | G20: Crude Oil and Refined | H20: Ref Diffs mt | I20: Bilateral | J20: ICES | K20: Oil | L20: SFS
A21: Fuel Oil Diff - Fuel Oil 180 CST Singapore vs 3.5% FOB Rotterdam Barges Future | B21: 88 | C21: SFS | D21: SFS | E21: OW | F21: NM80 | G21: Crude Oil and Refined Products | H21: Ref Diffs mt | I21: ICEU | J21: IFEU | K21: Oil | L21: SFS
A22: Singapore Naphtha Future | B22: 95 | C22: NPT | D22: NPT | E22: Q1 | G22: Crude Oil and Refined Products | H22: RefOutright bbl | I22: ICEU | J22: IFEU | K22: Oil | L22: NPT
A23: Jet Fuel Outright - Singapore Jet Kerosene Future | B23: 124 | C23: SRS | D23: SRS | E23: SR | F23: QH61 | G23: Crude Oil and Refined Products | H23: RefOutright bbl | I23: ICEU | J23: IFEU | K23: Oil | L23: SRS
A24: Singapore Jet Kerosene Swap | B24: 124 | C24: SRS | D24: SRS | E24: SR | F24: QH61 | G24: Crude Oil and Refined | H24: RefOutright bbl | I24: Bilateral | J24: ICES | K24: Oil | L24: SRS
A25: Fuel Oil Crack - USGC HSFO (Platts) vs WTI 1st Line Future | B25: 166 | C25: GUF | D25: GUF | E25: Q3 | G25: Crude Oil and Refined Products | H25: Am Cracks bbl | I25: ICEU | J25: IFED | K25: Oil Americas | L25: GUF
A26: Crude Diff - WTI vs Brent Bullet Future | B26: 171 | C26: TIB | D26: TIB | E26: U- | G26: Crude Oil and Refined Products | H26: Am Crude Diffs | I26: ICEU | J26: IFED | K26: Oil Americas | L26: TIB
A27: Brent Bullet Future | B27: 187 | C27: BNB | D27: BRN | E27: BN | F27: SG25 | G27: Crude Oil and Refined Products | H27: Crude Outrights | I27: ICEU | J27: IFEU | K27: Oil | L27: BNB
A28: Fuel Oil Diff - Fuel Oil 1% FOB Rotterdam Barges vs 1% FOB NWE Cargoes Future | B28: 200 | C28: FBC | D28: FBC | E28: FB | F28: QH72 | G28: Crude Oil and Refined Products | H28: Ref Diffs mt | I28: ICEU | J28: IFEU | K28: Oil | L28: FBC
A29: Fuel Oil 3.5% FOB Med Cargoes Future | B29: 222 | C29: FOM | D29: FOM | E29: 5 | F29: T034 | G29: Crude Oil and Refined Products | H29: Ref Outright mt | I29: ICEU | J29: IFEU | K29: Oil | L29: FOM
A30: Fuel Oil 1% FOB Rotterdam Barges Future | B30: 223 | C30: FOB | D30: FOB | E30: FO | F30: QH73 | G30: Crude Oil and Refined Products | H30: Ref Outright mt | I30: ICEU | J30: IFEU | K30: Oil | L30: FOB
A31: UK NBP Natural Gas Futures | B31: 236 | C31: M | D31: GWM | E31: WM | F31: 960 | G31: Natural Gas | H31: IPE Nat Gas | I31: ICEU | J31: IFEU | K31: IPE Natural Gas Futures | L31: GWM
A32: Brent Crude Futures | B32: 254 | C32: B | D32: BRN | E32: BC | F32: 952 | G32: Crude Oil and Refined Products | H32: IPE e-Brent | I32: ICEU | J32: IFEU | K32: IPE Brent Futures | L32: BRN
A33: Henry Penultimate Fixed Price Future | B33: 261 | C33: PHE | D33: HNG | E33: PH | F33: O759 | G33: Natural Gas | H33: Henry Hub (Pen) | I33: ICEU | J33: IFED | K33: Henry Hub | L33: PHE
A34: Fuel Oil Diff - Fuel Oil 180 CST Singapore vs 380 CST Singapore Future | B34: 266 | C34: STS | D34: STS | E34: ST | F34: QH63 | G34: Crude Oil and Refined Products | H34: Ref Diffs mt | I34: ICEU | J34: IFEU | K34: Oil | L34: STS
A35: Palo Verde Day-Ahead Peak Fixed Price Future | B35: 287 | C35: PVM | D35: PVM | E35: PV | F35: O940 | G35: Electricity | H35: Pwr West Term | I35: ICEU | J35: IFED | K35: Financial Power | L35: PVM
A36: CAISO SP-15 Day-Ahead Peak Fixed Price Future | B36: 288 | C36: SPM | D36: SPM | E36: SP | F36: O939 | G36: Electricity | H36: Pwr West Term | I36: ICEU | J36: IFED | K36: Financial Power | L36: SPM
A37: Mid-Columbia Day-Ahead Peak Fixed Price Future | B37: 318 | C37: MDC | D37: MDC | E37: MC | F37: N712 | G37: Electricity | H37: Pwr West Term | I37: ICEU | J37: IFED | K37: Financial Power | L37: MDC
A38: CAISO NP-15 Day-Ahead Peak Fixed Price Future | B38: 319 | C38: NPM | D38: NPM | E38: NP | F38: N713 | G38: Electricity | H38: Pwr West Term | I38: ICEU | J38: IFED | K38: Financial Power | L38: NPM
A39: Fuel Oil 380 CST Singapore Future | B39: 365 | C39: SYS | D39: SYS | E39: PF | F39: NM87 | G39: Crude Oil and Refined Products | H39: Ref Outright mt | I39: ICEU | J39: IFEU | K39: Oil | L39: SYS
A40: Fuel Oil 380 CST Singapore Swap | B40: 365 | C40: SYS | D40: SYS | E40: PF | F40: NM87 | G40: Crude Oil and Refined | H40: Ref Outright mt | I40: Bilateral | J40: ICES | K40: Oil | L40: SYS
A41: EUA Futures | B41: 390 | C41: C | D41: ECF | E41: CO | G41: Emissions | H41: EUA NDEX | I41: ICEU | J41: NDEX | K41: EU Emissions Allowances | L41: ECF
A42: PJM Western Hub Real-Time Off-Peak Daily Fixed Price Future | B42: 409 | C42: ODP | D42: ODP | E42: WO | F42: L781 | G42: Electricity | H42: Pwr EastOPDaily | I42: ICEU | J42: IFED | K42: Financial Power | L42: ODP
A43: PJM AEP Dayton Hub Real-Time Peak Daily Fixed Price Future | B43: 410 | C43: DDP | D43: DDP | E43: DP | F43: L778 | G43: Electricity | H43: Pwr East Daily | I43: ICEU | J43: IFED | K43: Financial Power | L43: DDP
A44: MISO Indiana Hub Real-Time Peak Daily Fixed Price Future | B44: 411 | C44: IDP | D44: IDP | E44: IP | F44: L780 | G44: Electricity | H44: Pwr East Daily | I44: ICEU | J44: IFED | K44: Financial Power | L44: IDP
A45: PJM NI Hub Real-Time Peak Daily Fixed Price Future | B45: 412 | C45: NDP | D45: NDP | E45: ND | F45: L779 | G45: Electricity | H45: Pwr East Daily | I45: ICEU | J45: IFED | K45: Financial Power | L45: NDP
A46: PJM Western Hub Real-Time Peak Daily Fixed Price Future | B46: 413 | C46: PDP | D46: PDP | E46: PP | F46: L777 | G46: Electricity | H46: Pwr East Daily | I46: ICEU | J46: IFED | K46: Financial Power | L46: PDP
A47: Henry Swing Future | B47: 414 | C47: HHD | D47: HHD | E47: HH | F47: L782 | G47: Natural Gas | H47: SwSwp HH Daily | I47: ICEU | J47: IFED | K47: Financial Gas | L47: HHD
A48: WTI Crude Futures | B48: 425 | C48: T | D48: WBS | E48: CS | F48: R755 | G48: Crude Oil and Refined Products | H48: ICE WTI | I48: ICEU | J48: IFEU | K48: ICE WTI Crude Futures | L48: WBS
A49: Henry Basis Future | B49: 430 | C49: HEN | D49: HEN | E49: NH | F49: NA89 | G49: Natural Gas | H49: Southeast Basis | I49: ICEU | J49: IFED | K49: Financial Gas | L49: HEN
A50: HSC Basis Future | B50: 431 | C50: HXS | D50: HXS | E50: NZ | F50: NA90 | G50: Natural Gas | H50: East TX Basis | I50: ICEU | J50: IFED | K50: Financial Gas | L50: HXS
A51: NWP Rockies Basis Future | B51: 432 | C51: NWR | D51: NWR | E51: NR | F51: NA82 | G51: Natural Gas | H51: RockiesNW Basis | I51: ICEU | J51: IFED | K51: Financial Gas | L51: NWR
A52: NWP Sumas Basis Future | B52: 433 | C52: NSU | D52: NSU | E52: NU | F52: NA87 | G52: Natural Gas | H52: RockiesNW Basis | I52: ICEU | J52: IFED | K52: Financial Gas | L52: NSU
A53: NGPL TXOK Basis Future | B53: 434 | C53: NTO | D53: NTO | E53: NY | F53: NE92 | G53: Natural Gas | H53: East TX Basis | I53: ICEU | J53: IFED | K53: Financial Gas | L53: NTO
... A62: ANR SW (Oklahoma) Basis Future | B62: 443 | C62: ANO | D62: ANO | E62: Y1 | F62: NG67 | G62: Natural Gas | H62: Midcont Basis | I62: ICEU | J62: IFED | K62: Financial Gas | L62: ANO
A63: Michcon Basis Future | B63: 444 | C63: NMC | D63: NMC | E63: OG | G63: Natural Gas | H63: Upper MW Basis | I63: ICEU | J63: IFED | K63: Financial Gas | L63: NMC
A64: NGPL Midcont Basis Future | B64: 445 | C64: MCO | D64: MCO | E64: OE | F64: NG66 | G64: Natural Gas | H64: Midcont Basis | I64: ICEU | J64: IFED | K64: Financial Gas | L64: MCO
A65: TETCO STX Basis Future | B65: 446 | C65: SXT | D65: SXT | E65: OI | F65: NG70 | G65: Natural Gas | H65: East TX Basis | I65: ICEU | J65: IFED | K65: Financial Gas | L65: SXT
A66: Transco Zone 3 Basis Future | B66: 447 | C66: STA | D66: STA | E66: OK | F66: NG72 | G66: Natural Gas | H66: Southeast Basis | I66: ICEU | J66: IFED | K66: Financial Gas | L66: STA
A67: NNG Ventura Basis Future | B67: 448 | C67: NVE | D67: NVE | E67: OC | F67: NG64 | G67: Natural Gas | H67: Upper MW Basis | I67: ICEU | J67: IFED | K67: Financial Gas | L67: NVE
A68: NNG Demarc Basis Future | B68: 449 | C68: DEM | D68: DEM | E68: OD | F68: NG65 | G68: Natural Gas | H68: Upper MW Basis | I68: ICEU | J68: IFED | K68: Financial Gas | L68: DEM
A69: CG Onshore Basis Future | B69: 450 | C69: CON | D69: CON | E69: Y2 | F69: NG71 | G69: Natural Gas | H69: Southeast Basis | I69: ICEU | J69: IFED | K69: Financial Gas | L69: CON
A70: AB NIT Basis Future | B70: 451 | C70: AEC | D70: AEC | E70: NB | F70: NA83 | G70: Natural Gas | H70: Canada Basis | I70: ICEU | J70: IFED | K70: Financial Gas | L70: AEC
A71: Chicago Basis Future | B71: 452 | C71: DGD | D71: DGD | E71: NC | F71: NA88 | G71: Natural Gas | H71: Upper MW Basis | I71: ICEU | J71: IFED | K71: Financial Gas | L71: DGD
A72: Malin Basis Future | B72: 453 | C72: MLN | D72: MLN | E72: NM | F72: NA85 | G72: Natural Gas | H72: RockiesNW Basis | I72: ICEU | J72: IFED | K72: Financial Gas | L72: MLN
A73: PG&E Citygate Basis Future | B73: 454 | C73: PGE | D73: PGE | E73: NQ | F73: NA84 | G73: Natural Gas | H73: Southwest Basis | I73: ICEU | J73: IFED | K73: Financial Gas | L73: PGE
A74: Socal Border Basis Future | B74: 455 | C74: SCL | D74: SCL | E74: NS | F74: NA86 | G74: Natural Gas | H74: Southwest Basis | I74: ICEU | J74: IFED | K74: Financial Gas | L74: SCL
A75: Henry Index Future | B75: 457 | C75: HIS | D75: HIS | E75: NX | F75: NA91 | G75: Natural Gas | H75: Southeast Index | I75: ICEU | J75: IFED | K75: Financial Gas | L75: HIS
... A88: Panhandle Swing Future | B88: 470 | C88: PSS | D88: PSS | E88: YW | F88: QM80 | G88: Natural Gas | H88: Midcont Swing | I88: ICEU | J88: IFED | K88: Financial Gas | L88: PSS
A89: EP San Juan Swing Future | B89: 471 | C89: SNS | D89: SNS | E89: QF | G89: Natural Gas | H89: Southwest Swing | I89: ICEU | J89: IFED | K89: Financial Gas | L89: SNS
A90: TCO Swing Future | B90: 472 | C90: CGS | D90: CGS | E90: YZ | F90: QM83 | G90: Natural Gas | H90: AppalachiaSwing | I90: ICEU | J90: IFED | K90: Financial Gas | L90: CGS
A91: Transco Zone 6 (NY) Swing Future | B91: 473 | C91: ZSS | D91: ZSS | E91: YX | F91: QM81 | G91: Natural Gas | H91: Northeast Swing | I91: ICEU | J91: IFED | K91: Financial Gas | L91: ZSS
A92: Waha Swing Future | B92: 474 | C92: WAS | D92: WAS | E92: HS | F92: SR16 | G92: Natural Gas | H92: Southwest Swing | I92: ICEU | J92: IFED | K92: Financial Gas | L92: WAS
A93: Eastern Gas South Swing Future | B93: 475 | C93: DSS | D93: DSS | E93: YY | F93: QM82 | G93: Natural Gas | H93: AppalachiaSwing | I93: ICEU | J93: IFED | K93: Financial Gas | L93: DSS
A94: EP Permian Swing Future | B94: 476 | C94: PES | D94: PES | E94: HM | F94: SR14 | G94: Natural Gas | H94: Southwest Swing | I94: ICEU | J94: IFED | K94: Financial Gas | L94: PES
A95: Michcon Swing Future | B95: 477 | C95: NMS | D95: NMS | E95: M5 | G95: Natural Gas | H95: Upper MW Swing | I95: ICEU | J95: IFED | K95: Financial Gas | L95: NMS
A96: NNG Ventura Swing Future | B96: 478 | C96: NNS | D96: NNS | E96: K9 | G96: Natural Gas | H96: Upper MW Swing | I96: ICEU | J96: IFED | K96: Financial Gas | L96: NNS
A97: NNG Demarc Swing Future | B97: 479 | C97: DES | D97: DES | E97: AP | G97: Natural Gas | H97: Upper MW Swing | I97: ICEU | J97: IFED | K97: Financial Gas | L97: DES
A98: TETCO M3 Swing Future | B98: 480 | C98: TSS | D98: TSS | E98: A2 | F98: SN14 | G98: Natural Gas | H98: Northeast Swing | I98: ICEU | J98: IFED | K98: Financial Gas | L98: TSS
A99: NWP Rockies Swing Future | B99: 481 | C99: RSS | D99: RSS | E99: RS | F99: QI04 | G99: Natural Gas | H99: RockiesNW Swing | I99: ICEU | J99: IFED | K99: Financial Gas | L99: RSS
A100: TETCO M3 Basis Future | B100: 489 | C100: TMT | D100: TMT | E100: NF | F100: NE85 | G100: Natural Gas | H100: Northeast Basis | I100: ICEU | J100: IFED | K100: Financial Gas | L100: TMT
A101: Heating Oil Futures | B101: 491 | C101: O | D101: UHO | E101: OM | F101: NF69 | G101: Crude Oil and Refined Products | H101: ICE Heating Oil | I101: ICEU | J101: IFEU | K101: ICE Heating Oil Futures | L101: UHO
A102: NYH (RBOB) Gasoline Futures | B102: 495 | C102: N | D102: UHU | E102: ON | F102: NF70 | G102: Crude Oil and Refined Products | H102: ICE RBOBGas | I102: ICEU | J102: IFEU | K102: ICE NYH (RBOB) Gasoline Futures | L102: UHU
A103: AB NIT Swing Future | B103: 501 | C103: ASS | D103: ASS | E103: YV | F103: QM79 | G103: Natural Gas | H103: Canada Swing | I103: ICEU | J103: IFED | K103: Financial Gas | L103: ASS
A104: Mid-Columbia Day-Ahead Off-Peak Fixed Price Future | B104: 502 | C104: OMC | D104: OMC | E104: OU | F104: NI02 | G104: Electricity | H104: Pwr West OPTerm | I104: ICEU | J104: IFED | K104: Financial Power | L104: OMC
A105: Palo Verde Day-Ahead Off-Peak Fixed Price Future | B105: 503 | C105: OVP | D105: OVP | E105: OR | F105: NI03 | G105: Electricity | H105: Pwr West OPTerm | I105: ICEU | J105: IFED | K105: Financial Power | L105: OVP
A106: CAISO NP-15 Day-Ahead Off-Peak Fixed Price Future | B106: 504 | C106: ONP | D106: ONP | E106: OS | F106: N104 | G106: Electricity | H106: Pwr West OPTerm | I106: ICEU | J106: IFED | K106: Financial Power | L106: ONP
A107: CAISO SP-15 Day-Ahead Off-Peak Fixed Price Future | B107: 505 | C107: OFP | D107: OFP | E107: OT | F107: NI05 | G107: Electricity | H107: Pwr West OPTerm | I107: ICEU | J107: IFED | K107: Financial Power | L107: OFP
A108: Malin Index Future | B108: 508 | C108: MIS | D108: MIS | E108: Y6 | F108: L336 | G108: Natural Gas | H108: RockiesNW Index | I108: ICEU | J108: IFED | K108: Financial Gas | L108: MIS
A109: Fuel Oil Crack - Fuel Oil 3.5% FOB Rotterdam Barges vs Brent 1st Line Future | B109: 516 | C109: BOB | D109: BOB | E109: PA | F109: NM84 | G109: Crude Oil and Refined Products | H109: Cracks mt | I109: ICEU | J109: IFEU | K109: Oil | L109: BOB
... A121: MISO Indiana Hub Real-Time Off-Peak Daily Fixed Price Future | B121: 554 | C121: IOP | D121: IOP | E121: QD | F121: NO12 | G121: Electricity | H121: Pwr EastOPDaily | I121: ICEU | J121: IFED | K121: Financial Power | L121: IOP
A122: Cocoa Futures | B122: 578 | C122: CC | D122: CC | E122: CY | F122: 2050 | G122: Cocoa | H122: Cocoa | I122: ICUS | J122: IFUS | K122: Cocoa | L122: CC
A123: Coffee C &#174; Futures | B123: 580 | C123: KC | D123: KC | E123: 43 | F123: 2065 | G123: Coffee | H123: Coffee C | I123: ICUS | J123: IFUS | K123: Coffee C | L123: KC
A124: Sugar No. 11 Futures | B124: 582 | C124: SB | D124: SB | E124: 27 | F124: 2055 | G124: Sugar | H124: Sugar No 11 | I124: ICUS | J124: IFUS | K124: Sugar No 11 | L124: SB
A125: FCOJ-A Futures | B125: 586 | C125: OJ | D125: OJ | E125: 96 | F125: 2200 | G125: Frozen Orange Juice | H125: FCOJ A | I125: ICUS | J125: IFUS | K125: FCOJ A | L125: OJ
A126: Cotton No. 2 Futures | B126: 588 | C126: CT | D126: CT | E126: 28 | F126: 2205 | G126: Cotton | H126: Cotton No 2 | I126: ICUS | J126: IFUS | K126: Cotton No 2 | L126: CT
A127: Brent Crude American-style Options | B127: 598 | C127: B | D127: BRN | E127: BC | F127: 952 | G127: Crude Oil and Refined Products | H127: O-IPE e-Brent | I127: ICEU | J127: IFEU | K127: IPE Brent Futures | L127: BRN
A128: WTI American-Style Options | B128: 600 | C128: T | D128: WBS | E128: CS | F128: R755 | G128: Crude Oil and Refined Products | H128: O-ICE WTI | I128: ICEU | J128: IFEU | K128: ICE WTI Crude Futures | L128: WBS
A129: US Dollar Index&reg; Futures | B129: 608 | C129: DX | D129: DX | E129: XD | F129: 2211 | G129: ICE U.S. Dollar Index (USDX) | H129: US Dollar Index | I129: ICUS | J129: IFUS | K129: US Dollar Index | L129: DX
A130: Dubai 1st Line Swap | B130: 637 | C130: DBI | D130: DBI | E130: DB | F130: OU44 | G130: Crude Oil and Refined | H130: Dubai Crude | I130: ICEU | J130: ICES | K130: Platts Oil | L130: DBI
A131: Palo Verde Day-Ahead Off-Peak Daily Future | B131: 745 | C131: QVP | D131: QVP | E131: QV | F131: OU48 | G131: Electricity | H131: Pwr WestOPDaily | I131: ICEU | J131: IFED | K131: Financial Power | L131: QVP
...
